plonetheme.cleanblog-1.2.1-py2.7-nspkg.pth
plonetheme/clean_blog/__init__.py
plonetheme/clean_blog/configure.zcml
plonetheme/clean_blog/interfaces.py
plonetheme/clean_blog/setuphandlers.py
plonetheme/clean_blog/testing.py
plonetheme/clean_blog/browser/__init__.py
plonetheme/clean_blog/browser/configure.zcml
plonetheme/clean_blog/browser/overrides/.gitkeep
plonetheme/clean_blog/browser/static/.gitkeep
plonetheme/clean_blog/locales/plonetheme.clean_blog.pot
plonetheme/clean_blog/locales/update.sh
plonetheme/clean_blog/profiles/default/browserlayer.xml
plonetheme/clean_blog/profiles/default/metadata.xml
plonetheme/clean_blog/profiles/default/theme.xml
plonetheme/clean_blog/profiles/uninstall/browserlayer.xml
plonetheme/clean_blog/profiles/uninstall/theme.xml
plonetheme/clean_blog/tests/__init__.py
plonetheme/clean_blog/tests/test_robot.py
plonetheme/clean_blog/tests/test_setup.py
plonetheme/clean_blog/tests/robot/test_example.robot
plonetheme/clean_blog/theme/LICENSE
plonetheme/clean_blog/theme/index.html
plonetheme/clean_blog/theme/manifest.cfg
plonetheme/clean_blog/theme/preview.png
plonetheme/clean_blog/theme/rules.xml
plonetheme/clean_blog/theme/css/bootstrap.min.css
plonetheme/clean_blog/theme/css/main.css
plonetheme/clean_blog/theme/css/main.css.map
plonetheme/clean_blog/theme/fonts/glyphicons-halflings-regular.eot
plonetheme/clean_blog/theme/fonts/glyphicons-halflings-regular.svg
plonetheme/clean_blog/theme/fonts/glyphicons-halflings-regular.ttf
plonetheme/clean_blog/theme/fonts/glyphicons-halflings-regular.woff
plonetheme/clean_blog/theme/fonts/glyphicons-halflings-regular.woff2
plonetheme/clean_blog/theme/img/home-bg.jpg
plonetheme/clean_blog/theme/js/clean-blog.js
plonetheme/clean_blog/theme/js/clean-blog.min.js
plonetheme/clean_blog/theme/less/clean_blog-compiled.css.map
plonetheme/clean_blog/theme/less/main.less
plonetheme/clean_blog/theme/less/partials/base.less
plonetheme.cleanblog-1.2.1.dist-info/DESCRIPTION.rst
plonetheme.cleanblog-1.2.1.dist-info/METADATA
plonetheme.cleanblog-1.2.1.dist-info/RECORD
plonetheme.cleanblog-1.2.1.dist-info/WHEEL
plonetheme.cleanblog-1.2.1.dist-info/entry_points.txt
plonetheme.cleanblog-1.2.1.dist-info/metadata.json
plonetheme.cleanblog-1.2.1.dist-info/namespace_packages.txt
plonetheme.cleanblog-1.2.1.dist-info/top_level.txt
